__cubao_tippecanoe_tippecanoe.exe
__cubao_tippecanoe_jsontool.exe
__cubao_tippecanoe_decode.exe
_pybind11_tippecanoe.cpython-310-x86_64-linux-gnu.so
__cubao_tippecanoe_enumerate.exe
__cubao_tippecanoe_tile-join.exe
__cubao_tippecanoe_overzoom.exe
cubao_tippecanoe-0.0.2.dist-info/LICENSE.md
cubao_tippecanoe-0.0.2.dist-info/top_level.txt
cubao_tippecanoe-0.0.2.dist-info/WHEEL
cubao_tippecanoe-0.0.2.dist-info/METADATA
cubao_tippecanoe-0.0.2.dist-info/RECORD
cubao_tippecanoe/__init__.py
cubao_tippecanoe/__main__.py
