Metadata-Version: 2.1
Name: cubao_tippecanoe
Version: 0.0.2
Summary: standalone tippecanoe
Home-page: https://github.com/cubao/cubao-tippecanoe
Author: tzx
Author-email: dvorak4tzx@gmail.com
License-File: LICENSE.md
